odoo/addons/ssi_product_usage_account_type/README.rst
odoo/addons/ssi_product_usage_account_type/__init__.py
odoo/addons/ssi_product_usage_account_type/__manifest__.py
odoo/addons/ssi_product_usage_account_type/data/product_usage_type_data.xml
odoo/addons/ssi_product_usage_account_type/models/__init__.py
odoo/addons/ssi_product_usage_account_type/models/mixin_product_usage_m2o_configurator.py
odoo/addons/ssi_product_usage_account_type/models/product_account.py
odoo/addons/ssi_product_usage_account_type/models/product_category.py
odoo/addons/ssi_product_usage_account_type/models/product_category_account.py
odoo/addons/ssi_product_usage_account_type/models/product_product.py
odoo/addons/ssi_product_usage_account_type/models/product_template.py
odoo/addons/ssi_product_usage_account_type/models/product_template_account.py
odoo/addons/ssi_product_usage_account_type/models/product_usage_type.py
odoo/addons/ssi_product_usage_account_type/security/ir.model.access.csv
odoo/addons/ssi_product_usage_account_type/security/res_group_data.xml
odoo/addons/ssi_product_usage_account_type/static/description/icon.png
odoo/addons/ssi_product_usage_account_type/templates/product_usage_m2_configurator_templates.xml
odoo/addons/ssi_product_usage_account_type/views/product_category_views.xml
odoo/addons/ssi_product_usage_account_type/views/product_product_views.xml
odoo/addons/ssi_product_usage_account_type/views/product_template_views.xml
odoo/addons/ssi_product_usage_account_type/views/product_usage_type_views.xml
odoo14_addon_ssi_product_usage_account_type-14.0.1.4.0.dist-info/METADATA
odoo14_addon_ssi_product_usage_account_type-14.0.1.4.0.dist-info/WHEEL
odoo14_addon_ssi_product_usage_account_type-14.0.1.4.0.dist-info/top_level.txt
odoo14_addon_ssi_product_usage_account_type-14.0.1.4.0.dist-info/RECORD
